forbin/__init__.py
forbin-0.1.dist-info/LICENSE.txt
forbin-0.1.dist-info/METADATA
forbin-0.1.dist-info/WHEEL
forbin-0.1.dist-info/entry_points.txt
forbin-0.1.dist-info/top_level.txt
forbin-0.1.dist-info/RECORD
